{
  "user_id": 1,
  "data": {
    "x_data_type": "weight_on_x",
    "y_data_type": "height_on_y",
    "x": [
      {
        "date": "2012-11-05",
        "value": 125.4
      },
      {
        "date": "2022-11-03",
        "value": 105.4
      },
      {
        "date": "2022-11-01",
        "value": 85.4
      },
      {
        "date": "2020-11-03",
        "value": 795.1
      },
      {
        "date": "2019-11-03",
        "value": 195.4
      },
      {
        "date": "2018-11-03",
        "value": 155.4
      }
    ],
    "y": [
      {
        "date": "2022-11-01",
        "value": 75.2
      },
      {
        "date": "2022-11-03",
        "value": 115.5
      },
      {
        "date": "2022-11-03",
        "value": 155.7
      },
      {
        "date": "2020-11-03",
        "value": 575.4
      },
      {
        "date": "2019-11-03",
        "value": 205.4
      },
      {
        "date": "2018-11-03",
        "value": 155.4
      }
    ]
  }
}